pyhtmlify/__init__.py
pyhtmlify/HTMLElements/HTMLElements-LAPTOP-Q9M3LM7K.py
pyhtmlify/HTMLElements/HTMLElements.py
pyhtmlify/HTMLElements/__init__.py
pyhtmlify/HTMLTags/__init__.py
pyhtmlify/HTMLTags/tags.py
pyhtmlify/cli/__init__.py
pyhtmlify/cli/cli.py
pyhtmlify-0.1.8.dist-info/LICENSE
pyhtmlify-0.1.8.dist-info/METADATA
pyhtmlify-0.1.8.dist-info/WHEEL
pyhtmlify-0.1.8.dist-info/entry_points.txt
pyhtmlify-0.1.8.dist-info/top_level.txt
pyhtmlify-0.1.8.dist-info/RECORD
