Metadata-Version: 2.1
Name: pyhtmlify
Version: 0.1.8
Summary: HTML in Pure Python
Home-page: https://github.com/Peggun/pyhtml
Author: Peggun
Author-email: peggundev@gmail.com
Classifier: Programming Language :: Python :: 3.0
Classifier: License :: OSI Approved :: GNU General Public License v3 (GPLv3)
Classifier: Operating System :: OS Independent
Requires-Python: >=3.6
License-File: LICENSE
Requires-Dist: certifi==2024.7.4
Requires-Dist: charset-normalizer==3.3.2
Requires-Dist: docutils==0.21.2
Requires-Dist: idna==3.7
Requires-Dist: importlib-metadata==8.4.0
Requires-Dist: jaraco.classes==3.4.0
Requires-Dist: jaraco.context==6.0.1
Requires-Dist: jaraco.functools==4.0.2
Requires-Dist: keyring==25.3.0
Requires-Dist: markdown-it-py==3.0.0
Requires-Dist: mdurl==0.1.2
Requires-Dist: more-itertools==10.4.0
Requires-Dist: nh3==0.2.18
Requires-Dist: pkginfo==1.10.0
Requires-Dist: Pygments==2.18.0
Requires-Dist: readme-renderer==44.0
Requires-Dist: requests==2.32.3
Requires-Dist: requests-toolbelt==1.0.0
Requires-Dist: rfc3986==2.0.0
Requires-Dist: rich==13.7.1
Requires-Dist: setuptools>=64
Requires-Dist: urllib3==2.2.2
Requires-Dist: zipp==3.20.0
Requires-Dist: beautifulsoup4==4.12.3
